rl_temple/__init__.py
rl_temple/algos/dqn.py
rl_temple/environments/__init__.py
rl_temple/environments/snake_env.py
rl_temple/logging/__init__.py
rl_temple/logging/tensorboard_logger.py
rl_temple/models/__init__.py
rl_temple/models/cnn.py
rl_temple/models/factory.py
rl_temple/models/mlp.py
rl_temple/models/utils.py
rl_temple-0.0.1a0.dist-info/LICENSE
rl_temple-0.0.1a0.dist-info/METADATA
rl_temple-0.0.1a0.dist-info/WHEEL
rl_temple-0.0.1a0.dist-info/RECORD
