Metadata-Version: 2.1
Name: rl_temple
Version: 0.0.1a0
Summary: Toolbox for training RL agents
License: MIT
Author: Cem Alpturk
Author-email: cem.alpturk@gmail.com
Requires-Python: >=3.11,<3.12
Classifier: License :: OSI Approved :: MIT License
Classifier: Programming Language :: Python :: 3
Classifier: Programming Language :: Python :: 3.11
Requires-Dist: gymnasium (>=0.29.1,<0.30.0)
Requires-Dist: matplotlib (>=3.9.0,<4.0.0)
Requires-Dist: moviepy (>=1.0.3,<2.0.0)
Requires-Dist: numpy (>=1.26.4,<2.0.0)
Requires-Dist: pygame (>=2.6.0,<3.0.0)
Requires-Dist: tensorboard (>=2.17.0,<3.0.0)
Requires-Dist: torch (>=2.3.1,<3.0.0)
Requires-Dist: tqdm (>=4.66.4,<5.0.0)
Requires-Dist: wandb (>=0.17.3,<0.18.0)
